joatmon/__init__.py
joatmon/ai/__init__.py
joatmon/ai/memory.py
joatmon/ai/policy.py
joatmon/ai/random.py
joatmon/ai/utility.py
joatmon/ai/models/__init__.py
joatmon/ai/models/core.py
joatmon/ai/models/ddpg.py
joatmon/ai/models/dqn.py
joatmon/ai/models/td3.py
joatmon/ai/network/__init__.py
joatmon/ai/network/core.py
joatmon/ai/network/ddpg.py
joatmon/ai/network/dqn.py
joatmon/ai/network/td3.py
joatmon/analysis/__init__.py
joatmon/array/__init__.py
joatmon/array/array.py
joatmon/array/functional.py
joatmon/array/random.py
joatmon/assistant/__init__.py
joatmon/assistant/api.py
joatmon/assistant/runnable.py
joatmon/assistant/service.py
joatmon/assistant/task.py
joatmon/assistant/action/__init__.py
joatmon/assistant/action/help.py
joatmon/assistant/action/run.py
joatmon/core/__init__.py
joatmon/core/context.py
joatmon/core/decorators.py
joatmon/core/event.py
joatmon/core/exception.py
joatmon/core/lock.py
joatmon/core/serializable.py
joatmon/core/utility.py
joatmon/decorator/__init__.py
joatmon/decorator/auth.py
joatmon/decorator/cache.py
joatmon/decorator/database.py
joatmon/decorator/debug.py
joatmon/decorator/exception.py
joatmon/decorator/logger.py
joatmon/decorator/message.py
joatmon/decorator/otp.py
joatmon/decorator/retry.py
joatmon/decorator/version.py
joatmon/decorator/web.py
joatmon/game/__init__.py
joatmon/game/core.py
joatmon/game/sokoban.py
joatmon/game/assets/sokoban/sprites/block.png
joatmon/game/assets/sokoban/sprites/goal.png
joatmon/game/assets/sokoban/sprites/obstacle.png
joatmon/game/assets/sokoban/sprites/player.png
joatmon/game/assets/sokoban/xmls/default.xml
joatmon/game/assets/sokoban/xmls/medium.xml
joatmon/image/__init__.py
joatmon/nn/__init__.py
joatmon/nn/core.py
joatmon/nn/functional.py
joatmon/nn/init.py
joatmon/nn/processing.py
joatmon/nn/utility.py
joatmon/nn/layer/__init__.py
joatmon/nn/layer/batchnorm.py
joatmon/nn/layer/conv.py
joatmon/nn/layer/dropout.py
joatmon/nn/layer/flatten.py
joatmon/nn/layer/linear.py
joatmon/nn/layer/lstm.py
joatmon-3.2.0.dist-info/LICENSE
joatmon-3.2.0.dist-info/METADATA
joatmon-3.2.0.dist-info/WHEEL
joatmon-3.2.0.dist-info/top_level.txt
joatmon-3.2.0.dist-info/RECORD
