Metadata-Version: 2.1
Name: joatmon
Version: 3.2.0
Summary: General Purpose Python Library
Home-page: https://github.com/malkoch/joatmon
Download-URL: https://github.com/malkoch/joatmon/tags
Author: Hamitcan Malkoç
Author-email: hamitcanmalkoc@gmail.com
License: MIT
Keywords: joatmon ml idm automation iva
Classifier: Development Status :: 5 - Production/Stable
Classifier: Intended Audience :: Developers
Classifier: Topic :: Software Development
Classifier: Topic :: Software Development :: Libraries
Classifier: Topic :: Software Development :: Libraries :: Python Modules
Classifier: Programming Language :: Python :: 3
Classifier: Programming Language :: Python :: 3.9
Classifier: Programming Language :: Python :: 3.10
Requires-Python: >=3.9.1
License-File: LICENSE
Requires-Dist: bumpversion
Requires-Dist: mkgendocs
Provides-Extra: ai
Requires-Dist: numpy ; extra == 'ai'
Provides-Extra: all
Requires-Dist: pandas ; extra == 'all'
Requires-Dist: transitions ; extra == 'all'
Requires-Dist: six ; extra == 'all'
Requires-Dist: pymunk ; extra == 'all'
Requires-Dist: async-exit-stack ; extra == 'all'
Requires-Dist: opencv-python ; extra == 'all'
Requires-Dist: pika ; extra == 'all'
Requires-Dist: pygame ; extra == 'all'
Requires-Dist: confluent-kafka ; extra == 'all'
Requires-Dist: pyotp ; extra == 'all'
Requires-Dist: numpy ; extra == 'all'
Requires-Dist: redis ; extra == 'all'
Requires-Dist: elasticsearch ; extra == 'all'
Requires-Dist: couchbase ; extra == 'all'
Requires-Dist: SpeechRecognition ; extra == 'all'
Requires-Dist: psycopg2 ; extra == 'all'
Requires-Dist: pymongo ; extra == 'all'
Requires-Dist: gym ; extra == 'all'
Requires-Dist: pyjwt ; extra == 'all'
Provides-Extra: analysis
Requires-Dist: numpy ; extra == 'analysis'
Requires-Dist: pandas ; extra == 'analysis'
Provides-Extra: array
Requires-Dist: transitions ; extra == 'array'
Provides-Extra: assistant
Provides-Extra: decorator
Requires-Dist: async-exit-stack ; extra == 'decorator'
Provides-Extra: game
Requires-Dist: gym ; extra == 'game'
Requires-Dist: opencv-python ; extra == 'game'
Requires-Dist: pygame ; extra == 'game'
Requires-Dist: pymunk ; extra == 'game'
Provides-Extra: image
Requires-Dist: opencv-python ; extra == 'image'
Provides-Extra: nn
Requires-Dist: numpy ; extra == 'nn'
Requires-Dist: six ; extra == 'nn'
Provides-Extra: orm
Provides-Extra: plugin
Requires-Dist: pyjwt ; extra == 'plugin'
Requires-Dist: redis ; extra == 'plugin'
Requires-Dist: couchbase ; extra == 'plugin'
Requires-Dist: elasticsearch ; extra == 'plugin'
Requires-Dist: pymongo ; extra == 'plugin'
Requires-Dist: psycopg2 ; extra == 'plugin'
Requires-Dist: confluent-kafka ; extra == 'plugin'
Requires-Dist: pika ; extra == 'plugin'
Requires-Dist: pyotp ; extra == 'plugin'
Provides-Extra: structure
Provides-Extra: system
Requires-Dist: opencv-python ; extra == 'system'
Requires-Dist: SpeechRecognition ; extra == 'system'
Requires-Dist: numpy ; extra == 'system'
